[
  {
    "key": "assign|EM_Popper|88a9bc6d5f44",
    "original": "EM Popper",
    "translation": "",
    "context": "<<POS:05910424>> XPLOSIVECONSUMABLE,e.shortName='EM Popper'"
  },
  {
    "key": "assign|EM_Popper|506c9b453d7f",
    "original": "EM Popper",
    "translation": "",
    "context": "<<POS:05910447>> ortName=\"EM Popper\",e.longName='EM Popper'"
  },
  {
    "key": "assign|an_EM_Popper|e8782ce06cf2",
    "original": "an EM Popper",
    "translation": "",
    "context": "<<POS:05910530>> ase(e.longName)),e.description='an EM Popper'"
  },
  {
    "key": "assign|Also_called_a_rebel_s_best_friend_the_EM_Popper_is_a_small_ar|6fd72532ebd2",
    "original": "Also called a “rebel’s best friend”, the EM Popper is a small-area electromagnetic pulse grenade that can take out shields as easily as it fries computer chips and communication devices. More robust security systems often have built-in protections and backups against EMP, but such contingencies can hardly be taken to the field. Needless to say, the property damage caused by EM Poppers is sufficient to drive the zaibatsu crazy.",
    "translation": "",
    "context": "<<POS:05910555>> ption=\"an EM Popper\",e.tooltip='Also called a “rebel’s best friend”, the EM Popper is a smal'"
  },
  {
    "key": "output|Pulling_the_pin_on_a_grenade_without_a_target_to_throw_it_at_wou|41a5ff26802c",
    "original": "Pulling the pin on a grenade without a target to throw it at would be pretty dumb now, wouldn’t it?",
    "translation": "",
    "context": "<<POS:05911555>> output(\"Pulling the pin on a grenade without a target to throw it at would be pretty dumb now, wouldn’t it?\\n\")"
  },
  {
    "key": "output.expr|var0_var1_considers_it_unwise_to_use_a_grenade_outside_of|bf9bd1dcc7d1",
    "original": "{var0}+{var1}+\" considers it unwise to use a grenade outside of combat.",
    "translation": "",
    "context": "<<POS:05911682>> <<VARS:var0=e.capitalA,var1=e.short>> output(e.capitalA+e.short+\" considers it unwise to use a grenade outside of combat.\\n\")"
  },
  {
    "key": "combat|It_seems_you_have_no_target_to_use_your_EM_Popper_on|f775a7cf0559",
    "original": "It seems you have no target to use your EM Popper on.",
    "translation": "",
    "context": "<<POS:05911928>> combatOutput(\"It seems you have no target to use your EM Popper on.\",null,t)"
  },
  {
    "key": "combat.expr|var1_capitalize_var0_produces_an_EM_Popper_but_with_no_t|51bf19dc0f98",
    "original": "{var1}.capitalize({var0})+\" produces an EM Popper--but with no target to use it on, \"+{var2}.mfn(\"he\",\"she\",\"it\")+\" puts it away.",
    "translation": "",
    "context": "<<POS:05912004>> <<VARS:var0=t.getCombatName(),!1,var1=g.m,var2=t>> combatOutput(g.m.capitalize(t.getCombatName(),!1)+\" produces an EM Popper--but with no target to use it on, \"+t.mfn(\"he\",\"she\",\"it\")+\" puts it away.\",null,t)"
  },
  {
    "key": "combat.expr|You_pull_out_an_EM_Popper_and_huck_it_in_the_direction_of_var|41cca2a97abf",
    "original": "You pull out an EM Popper and huck it in the direction of \"+{var0}.getCombatName()+\".",
    "translation": "",
    "context": "<<POS:05912219>> <<VARS:var0=a>> combatOutput(\"You pull out an EM Popper and huck it in the direction of \"+a.getCombatName()+\".\",null,t)"
  },
  {
    "key": "combat.expr|var1_capitalize_var0_produces_an_EM_Popper_and_hucks_it_i|cdcbb823fb0f",
    "original": "{var1}.capitalize({var0})+\" produces an EM Popper and hucks it in your direction!",
    "translation": "",
    "context": "<<POS:05912339>> <<VARS:var0=t.getCombatName(),!1,var1=g.m>> combatOutput(g.m.capitalize(t.getCombatName(),!1)+\" produces an EM Popper and hucks it in your direction!\",null,t)"
  },
  {
    "key": "output.expr|var1_capitalize_var0_produces_an_EM_Popper_and_hucks_it_i|a373d7353152",
    "original": "{var1}.capitalize({var0})+\" produces an EM Popper and hucks it in the direction of \"+{var2}.getCombatName()+\"!",
    "translation": "",
    "context": "<<POS:05912448>> <<VARS:var0=t.getCombatName(),!1,var1=g.m,var2=a>> output(g.m.capitalize(t.getCombatName(),!1)+\" produces an EM Popper and hucks it in the direction of \"+a.getCombatName()+\"!\",null,t)"
  },
  {
    "key": "combat.expr|var0_var1_var2_are_is_caught_in_the_explosio|d0a0d3b7cd50",
    "original": "\"+{var0}+{var1}+\" \"+({var2}?\"are\":\"is\")+\" caught in the explosion!",
    "translation": "",
    "context": "<<POS:05912747>> <<VARS:var0=i.capitalA,var1=i.uniqueName,var2=i.isPlural>> combatOutput(\"\\n\\n\"+i.capitalA+i.uniqueName+\" \"+(i.isPlural?\"are\":\"is\")+\" caught in the explosion!\",null,i)"
  },
  {
    "key": "combat|The_electronic_burst_from_the_grenade_has_temporarily_disrupted|e9cfc81e4b0c",
    "original": "The electronic burst from the grenade has temporarily disrupted your systems!",
    "translation": "",
    "context": "<<POS:05912985>> combatOutput(\"The electronic burst from the grenade has temporarily disrupted your systems!\",null,i)"
  },
  {
    "key": "combat.expr|The_electronic_burst_from_the_grenade_has_temporarily_disrupted|093420bcef78",
    "original": "The electronic burst from the grenade has temporarily disrupted \"+{var0}+{var1}+\"’s systems!",
    "translation": "",
    "context": "<<POS:05913168>> <<VARS:var0=i.a,var1=i.short>> combatOutput(\"The electronic burst from the grenade has temporarily disrupted \"+i.a+i.short+\"’s systems!\",null,i)"
  }
]