[{"key": "assign|Anchor_Piercing|b9d840fffcca", "original": "Anchor Piercing", "translation": "", "context": "<<POS:07379124>> .shortName=\"Anchor\",e.longName='Anchor Piercing'"}, {"key": "assign|a_single_anchor_shaped_metal_decoration_with_a_hoop_at_the_base|c3d0469791cd", "original": "a single anchor shaped metal decoration with a hoop at the base of the shank", "translation": "", "context": "<<POS:07379213>> ase(e.longName)),e.description='a single anchor shaped metal decoration with a hoop at the b'"}, {"key": "assign|A_metal_hook_shaped_like_an_old_boat_anchor_a_large_hoop_replac|84f43803a93b", "original": "A metal hook shaped like an old boat anchor, a large hoop replacing the chain fixture that would normally end the shank of the hook making it suitable for use as both a dangling piercing or when using one of the arms of the anchor directly.", "translation": "", "context": "<<POS:07379302>> e base of the shank\",e.tooltip='A metal hook shaped like an old boat anchor, a large hoop re'"}, {"key": "assign|Anchor_Piercings|2fd708f3f4d3", "original": "Anchor Piercings", "translation": "", "context": "<<POS:07380006>> shortName=\"Anchors\",e.longName='Anchor Piercings'"}, {"key": "assign|a_pair_of_anchor_shaped_metal_decorations_with_a_hoop_at_the_bas|0f0381ac79ec", "original": "a pair of anchor shaped metal decorations with a hoop at the base of the shanks", "translation": "", "context": "<<POS:07380096>> ase(e.longName)),e.description='a pair of anchor shaped metal decorations with a hoop at the'"}, {"key": "assign|A_pair_of_clean_metal_hooks_shaped_as_an_old_boat_anchor_a_hoop|3f6c72550de4", "original": "A pair of clean metal hooks shaped as an old boat anchor, a hoop replacing the chain fixture that would normally end the shank of each hook making them suitable for use as dangling piercings or when using the arms of the anchors directly.", "translation": "", "context": "<<POS:07380188>> base of the shanks\",e.tooltip='A pair of clean metal hooks shaped as an old boat anchor, a '"}]