[
  {
    "key": "assign|a_geddanium_crystal|61108a181981",
    "original": "a geddanium crystal",
    "translation": "",
    "context": "<<POS:10075554>>"
  },
  {
    "key": "assign|Geddanium_s_crystalline_form_is_extremely_rare_owing_to_its_pro|9cb491008d44",
    "original": "Geddanium’s crystalline form is extremely rare, owing to its propensity for elegantly alloying with other materials. While this property may have it highly sought-after for industrial and military uses, it also makes its pure crystalline form a treasured scarcity. Raw crystal Geddanium focuses laser beams cohesive enough to burn a target over a light year away, fearlessly bond with noble gasses in the right conditions, and even siphon exotic energies at high efficiencies.",
    "translation": "",
    "context": "<<POS:10075586>>"
  }
]