[
  {
    "key": "assign|a_logistics_suite|c77bebeb3908",
    "original": "a logistics suite",
    "translation": "",
    "context": "<<POS:07610338>>"
  },
  {
    "key": "assign|This_suite_comes_included_with_a_set_of_modular_spare_parts_and|48b16eeff63b",
    "original": "This suite comes included with a set of modular spare parts and a license for a specialized KihaCorp logistics platform, both of which serve to increase the overall efficiency of ship gadgets through careful power management and quick replacement of burned-out components.\\n\\n(+1 use of ship gadgets)",
    "translation": "",
    "context": "<<POS:07610368>>"
  }
]