[
  {
    "key": "assign|NOT_SET|3e41581f3af0",
    "original": "NOT SET",
    "translation": "",
    "context": "<<POS:10132887>> ,e.hairColor=\"cyan\",e.furColor='NOT SET'"
  },
  {
    "key": "assign|NOT_SET|3975c8b1d3a5",
    "original": "NOT SET",
    "translation": "",
    "context": "<<POS:10132910>> urColor=\"NOT SET\",e.scaleColor='NOT SET'"
  },
  {
    "key": "assign|NOT_SET|3975c8b1d3a5#1",
    "original": "NOT SET",
    "translation": "",
    "context": "<<POS:10132934>> eColor=\"NOT SET\",e.chitinColor='NOT SET'"
  },
  {
    "key": "assign|NOT_SET|3975c8b1d3a5#2",
    "original": "NOT SET",
    "translation": "",
    "context": "<<POS:10132959>> Color=\"NOT SET\",e.featherColor='NOT SET'"
  }
]