[{"key": "assign|R_Rags|02e897f94f64", "original": "R. Rags", "translation": "", "context": "<<POS:05698168>> pe=GLOBAL.CLOTHING,e.shortName='R. Rags'"}, {"key": "assign|rogue_s_rags|0aaed9796f01", "original": "rogue’s rags", "translation": "", "context": "<<POS:05698189>> shortName=\"R. Rags\",e.longName='rogue’s rags'"}, {"key": "assign|an_outfit_of_Raskvel_rags|5903a89bdb45", "original": "an outfit of Raskvel rags", "translation": "", "context": "<<POS:05698275>> ase(e.longName)),e.description='an outfit of Raskvel rags'"}, {"key": "assign|a_complex_array_of_rags_straps_and_pouches_fashioned_from_ruddy|7558f43aa7dc", "original": "a complex array of rags, straps and pouches fashioned from ruddy cloth. Similar, if more revealing, to what many of Novahome’s Raskvel wear. While surprisingly comfortable and easy to move around in, this getup provides makes no attempts to cover your groin or chest, letting everything hang free.", "translation": "", "context": "<<POS:05698313>> fit of Raskvel rags\",e.tooltip='a complex array of rags, straps and pouches fashioned from r'"}]