[{"key": "assign|SERA|73156b4e0a80", "original": "SERA", "translation": "", "context": "<<POS:10139445>> (this)).Name=\"\",e.UniqueParent='SERA'"}, {"key": "assign|human|79762f9477c6", "original": "human", "translation": "", "context": "<<POS:10139467>> ueParent=\"SERA\",e.originalRace='human'"}, {"key": "assign|fair|c67e27e97d8d", "original": "fair", "translation": "", "context": "<<POS:10139486>> riginalRace=\"human\",e.skinTone='fair'"}, {"key": "assign|red|a7c01b9c3823", "original": "red", "translation": "", "context": "<<POS:10139504>> \",e.skinTone=\"fair\",e.lipColor='red'"}, {"key": "assign|light_pink|158c74a39954", "original": "light pink", "translation": "", "context": "<<POS:10139524>> e.lipColor=\"red\",e.nippleColor='light pink'"}, {"key": "assign|brown|607ff2026cd1", "original": "brown", "translation": "", "context": "<<POS:10139548>> eColor=\"light pink\",e.eyeColor='brown'"}, {"key": "assign|hazel|73f9b5be22e0", "original": "hazel", "translation": "", "context": "<<POS:10139568>> e.eyeColor=\"brown\",e.hairColor='hazel'"}, {"key": "assign|NOT_SET|83b8382cc28d", "original": "NOT SET", "translation": "", "context": "<<POS:10139587>> e.hairColor=\"hazel\",e.furColor='NOT SET'"}, {"key": "assign|NOT_SET|3975c8b1d3a5", "original": "NOT SET", "translation": "", "context": "<<POS:10139610>> urColor=\"NOT SET\",e.scaleColor='NOT SET'"}, {"key": "assign|NOT_SET|3975c8b1d3a5#1", "original": "NOT SET", "translation": "", "context": "<<POS:10139634>> eColor=\"NOT SET\",e.chitinColor='NOT SET'"}, {"key": "assign|NOT_SET|3975c8b1d3a5#2", "original": "NOT SET", "translation": "", "context": "<<POS:10139659>> Color=\"NOT SET\",e.featherColor='NOT SET'"}]