[
  {
    "key": "assign|shield_aug_bracers|e013b5854ed5",
    "original": "shield aug bracers",
    "translation": "",
    "stage": 0,
    "context": "&lt;&lt;POS:05409225&gt;&gt;"
  },
  {
    "key": "assign|a_pair_of_shield_aug_bracers|b6fce48fe3a8",
    "original": "a pair of shield aug bracers",
    "translation": "",
    "stage": 0,
    "context": "&lt;&lt;POS:05409317&gt;&gt;"
  },
  {
    "key": "assign|These_thick_metal_bracers_cover_the_arm_all_the_way_from_the_wri|1473bac3f394",
    "original": "These thick metal bracers cover the arm all the way from the wrist to the midpoint of the forearm. Inside is the gleaming housing is a web of dense circuitry, embedded antennas, and multiple, redundant power packs. When turned on they significantly supplement projected shields.",
    "translation": "",
    "stage": 0,
    "context": "&lt;&lt;POS:05409358&gt;&gt;"
  }
]