[
  {
    "key": "output|You_press_the_applicator_tip_against_your_arm_and_barely_even_fe|6692a076676b",
    "original": "You press the applicator tip against your arm and barely even feel the telltale pinch of an injection. The rush of jittery, high-octane energy has your [pc.legOrLegs] bouncing and your jaw clenching.",
    "translation": "",
    "stage": 0,
    "context": "&lt;&lt;POS:07532271&gt;&gt;"
  },
  {
    "key": "combat|getting_a_quick_energy_boost|31d41e02cce2",
    "original": ", getting a quick energy boost.",
    "translation": "",
    "stage": 0,
    "context": "&lt;&lt;POS:07532618&gt;&gt;"
  },
  {
    "key": "combat|to_no_effect|1a76192218ca",
    "original": " to no effect.",
    "translation": "",
    "stage": 0,
    "context": "&lt;&lt;POS:07532666&gt;&gt;"
  },
  {
    "key": "output|to_no_effect|1a76192218ca",
    "original": " to no effect.",
    "translation": "",
    "stage": 0,
    "context": "&lt;&lt;POS:07532866&gt;&gt;"
  },
  {
    "key": "output|getting_a_quick_energy_boost|0c806b2424f6",
    "original": ", getting a quick energy boost.",
    "translation": "",
    "stage": 0,
    "context": "&lt;&lt;POS:07532824&gt;&gt;"
  }
]