[
  {
    "key": "button|Anno|dd8c960a4fc7",
    "original": "Anno",
    "translation": "",
    "context": "<<POS:00040456>>"
  },
  {
    "key": "button|Anno|898a4462a129",
    "original": "Anno",
    "translation": "",
    "context": "<<POS:00040681>>"
  },
  {
    "key": "button|Anno|898a4462a129#1",
    "original": "Anno",
    "translation": "",
    "context": "<<POS:00041310>>"
  },
  {
    "key": "button|Anno|898a4462a129#2",
    "original": "Anno",
    "translation": "",
    "context": "<<POS:00069837>>"
  },
  {
    "key": "combat|Anno_finally_brings_her_gun_to_bear_and_fires_pumping_her_enti|7a76815d0919",
    "original": " Anno finally brings her gun to bear and fires, pumping her entire magazine into the goo’s tits. The gray body explodes in a rain of goop, only to reform a moment later across the room as Anno slams a new mag into her holdout. <i>“I’m fine, I’m fine!”</i> Anno groans, rubbing at her throat, now visibly bruising.",
    "translation": "",
    "context": "<<POS:00070974>>"
  },
  {
    "key": "combat|one_of|b24eb23310f2",
    "original": " one of",
    "translation": "",
    "context": "<<POS:00071513>>"
  },
  {
    "key": "combat|the|53e2d0dff1a1",
    "original": " the",
    "translation": "",
    "context": "<<POS:00071537>>"
  },
  {
    "key": "combat|e_short_and_taps_a_key_on_her_tiny_computer_A_visible_targ|7bfb34690b1e",
    "original": " \"+e.short+\" and taps a key on her tiny computer. A visible targeting reticle forms around your opponent",
    "translation": "",
    "context": "<<POS:00071558>>"
  },
  {
    "key": "combat|s|a0c6b2f8f2cf",
    "original": "s",
    "translation": "",
    "context": "<<POS:00071702>>"
  },
  {
    "key": "combat|linking_up_with_your_own_equipment_in_the_process_n_b_Accurac|66924242e1f7",
    "original": ", linking up with your own equipment in the process.\\n<b>Accuracy increased!</b>",
    "translation": "",
    "context": "<<POS:00071720>>"
  },
  {
    "key": "combat|though_she_misses_her_target|9a2647fcc42d",
    "original": ", though she misses her target.",
    "translation": "",
    "context": "<<POS:00072543>>"
  },
  {
    "key": "combat|landing_a_solid_hit|6c9ba3fe8c99",
    "original": ", landing a solid hit",
    "translation": "",
    "context": "<<POS:00072596>>"
  },
  {
    "key": "combat|on_the_goo|924725ef2360",
    "original": " on the goo",
    "translation": "",
    "context": "<<POS:00072685>>"
  },
  {
    "key": "combat|on_t_a_t_uniqueName|964a203c1728",
    "original": " on \"+t.a+t.uniqueName",
    "translation": "",
    "context": "<<POS:00072713>>"
  },
  {
    "key": "combat|Her_attack_is_super_effective_while_her_target_is_incapacitated|13330021eefb",
    "original": " Her attack is super-effective while her target is incapacitated!",
    "translation": "",
    "context": "<<POS:00072774>>"
  }
]