[
  {
    "key": "output|ke_S_itemCollectedText|8cc5a6ee0d13",
    "original": "ke.S.itemCollectedText()",
    "translation": "",
    "context": "<<POS:12636852>>"
  },
  {
    "key": "button|Next|aa819b647721",
    "original": "Next",
    "translation": "",
    "context": "<<POS:12636998>> addButton(0,\"Next\",(function(){window.showInventory({force:!0})}))"
  },
  {
    "key": "button|Next|35b9a3540cff",
    "original": "Next",
    "translation": "",
    "context": "<<POS:12638202>> addButton(0,\"Next\",(function(){window.showInventory({force:!0})}))"
  },
  {
    "key": "button|Next|35b9a3540cff#1",
    "original": "Next",
    "translation": "",
    "context": "<<POS:12639371>> addButton(0,\"Next\",(function(){e&&e.quantity<=0&&(t.selectedItem=null,t.autoSortItems()),window.showInventory({force:!0})}))"
  },
  {
    "key": "button.tooltip|Use|bfc918a9747c",
    "original": "Use ",
    "translation": "",
    "context": "<<POS:12640306>> addButton(c++,o.buttonText,(function(){window.target=o,t.useItem(e,!1)}),Ot.m.toDisplayCase(\"target \".concat(\"PlayerCharacter\"===o.getClassName()?\"yourself\":o.getCombatName())),\"Use \".concat(e.description,\" on \").concat(\"PlayerCharacter\"===o.getClassName()?\"yourself\":o.nameDisplay(),\".\"))"
  },
  {
    "key": "button|Back|36725f5360e0",
    "original": "Back",
    "translation": "",
    "context": "<<POS:12640494>> addButton(14,\"Back\",(function(){window.target=null,window.popUIState()}))"
  }
]