[
  {
    "key": "combat|You_dodge_out_of_the_way|63cb4d6b27ac",
    "original": "You dodge out of the way!",
    "translation": "",
    "context": "<<POS:00178221>>"
  },
  {
    "key": "combat|this_capitalA_f_m_possessive_this_short_blinded_shots_fail_to|82b0b78a0544",
    "original": "this.capitalA+f.m.possessive(this.short)+\" blinded shots fail to connect!",
    "translation": "",
    "context": "<<POS:00178297>>"
  },
  {
    "key": "combat|this_capitalA_this_short_connects_with_this_mfn_his_her|8d3f6fb4a669",
    "original": "this.capitalA+this.short+\" connects with \"+this.mfn(\"his\",\"her\",\"its\")+\" massive gun!",
    "translation": "",
    "context": "<<POS:00178391>>"
  },
  {
    "key": "combat|Your_shield_crackles_but_holds|9df987dfaf47",
    "original": " Your shield crackles but holds.",
    "translation": "",
    "context": "<<POS:00178654>>"
  },
  {
    "key": "combat|There_is_a_concussive_boom_and_tingling_aftershock_of_energy_as|d753f27ee126",
    "original": " There is a concussive boom and tingling aftershock of energy as your shield is breached.",
    "translation": "",
    "context": "<<POS:00178703>>"
  },
  {
    "key": "combat|The_hit_carries_on_through_to_damage_you|0d605b9031f6",
    "original": " The hit carries on through to damage you!",
    "translation": "",
    "context": "<<POS:00178824>>"
  },
  {
    "key": "combat|Seeing_its_failure_the_machine_prepares_to_fire_again_this_ti|722039a9b805",
    "original": "Seeing its failure, the machine prepares to fire again - this time, though, the weapon explodes in a <i>different</i> way; you manage to duck as shrapnel goes flying over your head from the faulty firearm, and it’s the machina that takes the brunt of the blast. As you rise back up, you hear a pathetic sounding whir, petering out to nothing in short order. You’re left with a crumpled heap of a machine on the jungle floor.",
    "translation": "",
    "context": "<<POS:00178934>>"
  },
  {
    "key": "combat|Seeing_its_success_the_machine_tosses_away_the_firearm_in_short|270dacb351f2",
    "original": "Seeing its success the machine tosses away the firearm in short order, though as you fall backwards in pain you’re not really in the mindset to care.",
    "translation": "",
    "context": "<<POS:00179394>>"
  },
  {
    "key": "combat|You_manage_to_avoid_this_a_f_m_possessive_this_short_this|a2cab54d1d48",
    "original": "You manage to avoid \"+this.a+f.m.possessive(this.short)+\" \"+this.inventory.meleeWeapon.attackVerb+\".",
    "translation": "",
    "context": "<<POS:00181357>>"
  },
  {
    "key": "combat|e_customDodge|b19b22a6123e",
    "original": "e.customDodge",
    "translation": "",
    "context": "<<POS:00181530>>"
  },
  {
    "key": "combat|You_manage_to_avoid_this_a_f_m_possessive_this_short_this|7b0b300e75d9",
    "original": "You manage to avoid \"+this.a+f.m.possessive(this.short)+\" \"+this.inventory.meleeWeapon.attackVerb+\".",
    "translation": "",
    "context": "<<POS:00181559>>"
  },
  {
    "key": "combat|window_mimbraneFeetBonusEvadeBonus|3d5c95e6cfb8",
    "original": "window.mimbraneFeetBonusEvadeBonus()",
    "translation": "",
    "context": "<<POS:00181713>>"
  },
  {
    "key": "combat|this_capitalA_this_short_connects_with_this_mfn_his_her|b0b1f9248500",
    "original": "this.capitalA+this.short+\" connects with \"+this.mfn(\"his\",\"her\",\"its\")+\" \"+this.inventory.meleeWeapon.longName+\"!",
    "translation": "",
    "context": "<<POS:00181765>>"
  }
]