[
  {
    "key": "combat|It_seems_she_s_changed_her_skin_to_match_her_surroundings_like_i|34940f676a1c",
    "original": "It seems she’s changed her skin to match her surroundings like instant camouflage. You can still see her, but while she’s camouflaged it is going to be harder to hit her and dodge her attacks.",
    "translation": "",
    "context": "<<POS:01068190>>"
  },
  {
    "key": "combat|She_s_moved_around_too_much_and_suddenly_her_camouflage_is_usel|07cfc604fe16",
    "original": "She’s moved around too much, and suddenly her camouflage is useless. She seems to realize that as well, changing back to her usual skin tones. Now she’ll be easier to hit and dodge!",
    "translation": "",
    "context": "<<POS:01068710>>"
  },
  {
    "key": "combat|girlish|458f8b04f7d0",
    "original": " girlish",
    "translation": "",
    "context": "<<POS:01069020>>"
  },
  {
    "key": "combat|busty|edaf86a67a63",
    "original": " busty",
    "translation": "",
    "context": "<<POS:01069045>>"
  },
  {
    "key": "combat|huntress_grabs_the_sides_of_her_enemy_breasts_She_squeezes_t|6437a6d5f0c6",
    "original": " huntress grabs the sides of her [enemy.breasts]. She squeezes them and squirts a stream of [enemy.milk] at you.",
    "translation": "",
    "context": "<<POS:01069068>>"
  },
  {
    "key": "combat|You_dodge_the_enemy_milk_as_it_shoots_past_your_pc_ear_She|3be839e517de",
    "original": " You dodge the [enemy.milk] as it shoots past your [pc.ear]. She steadies her spear, moving back into her fighting stance.",
    "translation": "",
    "context": "<<POS:01069214>>"
  },
  {
    "key": "combat|You_are_splattered_with_her_enemy_milk_Fortunately_for_you|7233a3293ca4",
    "original": " You are splattered with her [enemy.milk]! Fortunately for you, your [pc.armor] is watertight and prevents any of the lust-inducing liquid from seeping into it.",
    "translation": "",
    "context": "<<POS:01069381>>"
  },
  {
    "key": "combat|You_are_splattered_with_her_enemy_milk_unable_to_get_it_off|399a76830fe9",
    "original": " You are splattered with her [enemy.milk], unable to get it off. All of a sudden, your cheeks begin to flush and you start feeling quite aroused...",
    "translation": "",
    "context": "<<POS:01069606>>"
  },
  {
    "key": "combat|You_are_splattered_with_her_enemy_milk_unable_to_get_it_off|947da8719670",
    "original": " You are splattered with her [enemy.milk], unable to get it off. All of a sudden, your cheeks begin to flush and you lose control to your limbs, falling to the ground. She’s leading into a follow-up attack...",
    "translation": "",
    "context": "<<POS:01069771>>"
  },
  {
    "key": "combat|meager|d48b4eeef50a",
    "original": " meager",
    "translation": "",
    "context": "<<POS:01070410>>"
  },
  {
    "key": "combat|sizable|3648f3697ad3",
    "original": " sizable",
    "translation": "",
    "context": "<<POS:01070434>>"
  },
  {
    "key": "combat|mounds_your_pc_groin_burning_with_arousal|a44f97cc3c68",
    "original": " mounds, your [pc.groin] burning with arousal.",
    "translation": "",
    "context": "<<POS:01070459>>"
  },
  {
    "key": "combat|short|a1a54b4e93a0",
    "original": " short",
    "translation": "",
    "context": "<<POS:01070725>>"
  },
  {
    "key": "combat|tentacle_skirt_begin_to|5f5db0518b7e",
    "original": " tentacle skirt begin to",
    "translation": "",
    "context": "<<POS:01070748>>"
  },
  {
    "key": "combat|awkwardly|e1946b980fe1",
    "original": " awkwardly",
    "translation": "",
    "context": "<<POS:01070808>>"
  },
  {
    "key": "combat|wrap_around_your_waist|1f196df95f31",
    "original": " wrap around your waist",
    "translation": "",
    "context": "<<POS:01070835>>"
  },
  {
    "key": "combat|and_lower_body|ce16697bceba",
    "original": " and lower body",
    "translation": "",
    "context": "<<POS:01070894>>"
  },
  {
    "key": "combat|You_can_feel_her_suckers_begin_to_stick_to_your_skin_she_s_t|92dae449bf9d",
    "original": ". You can feel her suckers begin to stick to your skin - she’s trying to pin you down!",
    "translation": "",
    "context": "<<POS:01070926>>"
  },
  {
    "key": "combat|You_forcibly_shake_her_off_of_you_it_s_a_close_call_If_she_d|456dde106d19",
    "original": " You forcibly shake her off of you; it’s a close call. If she’d pinned you, who knows what would have happened!",
    "translation": "",
    "context": "<<POS:01071046>>"
  },
  {
    "key": "combat|You_can_t_shake_her_off_you_as_she_wraps_around_your_lower_body|9c2ff12f8501",
    "original": " You can’t shake her off you as she wraps around your lower body and [pc.hips], pulling herself flush against your [pc.skin]. Her [enemy.breasts] are rubbing against you, coating you in her [enemy.milk]...",
    "translation": "",
    "context": "<<POS:01071175>>"
  },
  {
    "key": "combat|You_can_feel_your_cheeks_begin_to_flush_All_of_a_sudden_you_sta|b1c59639d76e",
    "original": "You can feel your cheeks begin to flush. All of a sudden you start to lose the ability to move your limbs, but not the ability to feel what’s happening to them. And what is happening feels <i>good</i>...",
    "translation": "",
    "context": "<<POS:01071401>>"
  },
  {
    "key": "combat|You_read_her_movements_and_avoid_being_tripped_She_only_succee|4a7b15ed0c60",
    "original": " You read her movements and avoid being tripped. She only succeeds at sweeping the ground with her sneaky strike.",
    "translation": "",
    "context": "<<POS:01072104>>"
  },
  {
    "key": "combat|You_re_struck_by_her_tail_falling_to_the_ground_She_gives_a_v|1e722531f3c2",
    "original": " You’re struck by her tail, falling to the ground. She gives a victorious grin, closing in on you. She’s leading into a follow-up attack...",
    "translation": "",
    "context": "<<POS:01072292>>"
  },
  {
    "key": "combat|You_re_struck_by_her_tail_falling_to_the_ground_and_hitting_yo|9390d3707db5",
    "original": " You’re struck by her tail, falling to the ground and hitting your head - hard. Your world spins as she closes in on you. You’re too disoriented to do anything about it...",
    "translation": "",
    "context": "<<POS:01072463>>"
  },
  {
    "key": "combat|You_jerk_out_of_the_way_and_she_connects_with_nothing_but_air|8303c5a3752a",
    "original": " You jerk out of the way and she connects with nothing but air. The alien girl spins around, returning to a neutral stance.",
    "translation": "",
    "context": "<<POS:01073112>>"
  },
  {
    "key": "combat|You_re_caught_off_guard_the_flat_end_cracking_against_the_side|ef0ac8cf15a3",
    "original": " You’re caught off guard, the flat end cracking against the side of your head. Pain shoots through your skull - her feint a success.",
    "translation": "",
    "context": "<<POS:01073389>>"
  },
  {
    "key": "combat|One_minute_you_re_fighting_the_next_you_re_seeing_stars_as_she|8f4cb46f0c0a",
    "original": " One minute you’re fighting, the next you’re seeing stars as she drives the flat end right into your temple. Your world spins, your head feeling as if it suddenly exploded.",
    "translation": "",
    "context": "<<POS:01073544>>"
  }
]